{
  "service_alerts": [
    {
      "id": "3bbffb8c-304f-4409-9800-9e700e0a1c65",
      "region": "fra",
      "subject": "Baremetal Controls and Console Outage",
      "start_date": "2026-05-29T22:55:00+00:00",
      "updated_at": "",
      "status": "resolved",
      "entries": [
        {
          "updated_at": "2026-05-29T22:55:00+00:00",
          "message": "We are currently experiencing an issue with the service which sends commands to Baremetal servers. The servers remain online but sending any commands from the console.vultr.com portal and the direct access console itself will not work. You may still access and reboot your servers via SSH if necessary during this time.\r\n\r\nWe greatly appreciate your patience in this matter.\r\n\r\nThank you\r\nThe Vultr.com Team"
        }
      ]
    },
    {
      "id": "f4086894-d6a6-4d28-a7ec-9b986af7888c",
      "region": "yto",
      "subject": "Toronto Scheduled Maintenance - 2026-06-02",
      "start_date": "2026-05-27T18:43:00+00:00",
      "updated_at": "",
      "status": "ongoing",
      "entries": [
        {
          "updated_at": "2026-05-27T18:43:00+00:00",
          "message": "Event Type: Network Upgrade\r\n\r\nWe are performing system changes in the Toronto location during the following scheduled maintenance window. \r\n\r\nStart Time: 2026-06-02 04:00:00 UTC\r\nEnd Time: 2026-06-02 09:00:00 UTC\r\n\r\nWe schedule higher impact maintenance events during off-peak times to maintain our ideal hosting environment. Our engineers make every effort to minimize system impact; however, Toronto instances may be unreachable for some, or all, of the scheduled maintenance window as we perform network, firmware, or host upgrades."
        }
      ]
    },
    {
      "id": "1128ddae-93ac-473a-92c6-4b718ce0215e",
      "region": "mia",
      "subject": "Miami Scheduled Maintenance - 2026-06-15",
      "start_date": "2026-05-27T18:35:00+00:00",
      "updated_at": "",
      "status": "ongoing",
      "entries": [
        {
          "updated_at": "2026-05-27T18:35:00+00:00",
          "message": "Event Type: Network Upgrade\r\n\r\nWe are performing system changes in the Miami location during the following scheduled maintenance window. \r\n\r\nStart Time: 2026-06-15 04:00:00 UTC\r\nEnd Time: 2026-06-15 09:00:00 UTC\r\n\r\nWe schedule higher impact maintenance events during off-peak times to maintain our ideal hosting environment. Our engineers make every effort to minimize system impact; however, Miami instances may be unreachable for some, or all, of the scheduled maintenance window as we perform network, firmware, or host upgrades."
        }
      ]
    },
    {
      "id": "c8348012-4430-4353-ab88-e7e8fb2dd575",
      "region": "mex",
      "subject": "Mexico City Scheduled Maintenance - 2026-06-10",
      "start_date": "2026-05-27T18:31:00+00:00",
      "updated_at": "",
      "status": "ongoing",
      "entries": [
        {
          "updated_at": "2026-05-27T18:31:00+00:00",
          "message": "Event Type: Network Upgrade\r\n\r\nWe are performing system changes in the Mexico City location during the following scheduled maintenance window. \r\n\r\nStart Time: 2026-06-10 06:00:00 UTC\r\nEnd Time: 2026-06-10 11:00:00 UTC\r\n\r\nWe schedule higher impact maintenance events during off-peak times to maintain our ideal hosting environment. Our engineers make every effort to minimize system impact; however, Mexico City instances may be unreachable for some, or all, of the scheduled maintenance window as we perform network, firmware, or host upgrades."
        }
      ]
    },
    {
      "id": "11ce1b56-c1ae-451f-9211-97851a408e14",
      "region": "lax",
      "subject": "Los Angeles Scheduled Maintenance - 2026-06-08",
      "start_date": "2026-05-27T18:23:00+00:00",
      "updated_at": "",
      "status": "ongoing",
      "entries": [
        {
          "updated_at": "2026-05-27T18:23:00+00:00",
          "message": "Event Type: Network Upgrade\r\n\r\nWe are performing system changes in the Los Angeles location during the following scheduled maintenance window. \r\n\r\nStart Time: 2026-06-08 07:00:00 UTC\r\nEnd Time: 2026-06-08 12:00:00 UTC\r\n\r\nWe schedule higher impact maintenance events during off-peak times to maintain our ideal hosting environment. Our engineers make every effort to minimize system impact; however, Los Angeles instances may be unreachable for some, or all, of the scheduled maintenance window as we perform network, firmware, or host upgrades."
        }
      ]
    },
    {
      "id": "c8f74f0b-775c-4376-aa37-56c88927cffd",
      "region": "sea",
      "subject": "Seattle Scheduled Maintenance - 2026-06-04",
      "start_date": "2026-05-27T18:16:00+00:00",
      "updated_at": "",
      "status": "ongoing",
      "entries": [
        {
          "updated_at": "2026-05-27T18:16:00+00:00",
          "message": "Event Type: Network Upgrade\r\n\r\nWe are performing system changes in the Seattle location during the following scheduled maintenance window. \r\n\r\nStart Time: 2026-06-04 07:00:00 UTC\r\nEnd Time: 2026-06-04 12:00:00 UTC\r\n\r\nWe schedule higher impact maintenance events during off-peak times to maintain our ideal hosting environment. Our engineers make every effort to minimize system impact; however, Seattle instances may be unreachable for some, or all, of the scheduled maintenance window as we perform network, firmware, or host upgrades."
        }
      ]
    },
    {
      "id": "83bdd30b-4e3e-4680-a75f-a40dd9f1d5c4",
      "region": "nrt",
      "subject": "Tokyo Scheduled Maintenance - 2026-06-08",
      "start_date": "2026-05-20T15:20:00+00:00",
      "updated_at": "",
      "status": "ongoing",
      "entries": [
        {
          "updated_at": "2026-05-20T15:20:00+00:00",
          "message": "Event Type: Network Upgrade\r\n\r\nWe are performing system changes in the Tokyo location during the following scheduled maintenance window. \r\n\r\nStart Time: 2026-06-08 15:05:00 UTC\r\nEnd Time: 2026-06-08 19:05:00 UTC\r\n\r\nWe schedule higher impact maintenance events during off-peak times to reduce impact to customer infrastructure. Our engineers make every effort to minimize system impact, however, network reachability to Tokyo instances may be affected for some, or all, of the scheduled maintenance window as we perform this work. While it’s important to be aware of start and end times of the maintenance window, due to our redundant network architecture, our engineers expect that you may see little to no impact at all while the work is performed."
        }
      ]
    },
    {
      "id": "179fa87e-e2b5-48de-badb-2b71526833ae",
      "region": "fra",
      "subject": "Frankfurt Scheduled Maintenance - 2026-06-09",
      "start_date": "2026-05-19T21:10:00+00:00",
      "updated_at": "",
      "status": "ongoing",
      "entries": [
        {
          "updated_at": "2026-05-19T21:10:00+00:00",
          "message": "Event Type: Network Upgrade\r\n\r\nWe are performing system changes in the Frankfurt location during the following scheduled maintenance window. \r\n\r\nStart Time: 2026-06-09 22:05:00 UTC\r\nEnd Time: 2026-06-10 02:05:00 UTC\r\n\r\nWe schedule higher impact maintenance events during off-peak times to reduce impact to customer infrastructure. Our engineers make every effort to minimize system impact, however, network reachability to Frankfurt instances may be affected for some, or all, of the scheduled maintenance window as we perform this work. While it’s important to be aware of start and end times of the maintenance window, due to our redundant network architecture, our engineers expect that you may see little to no impact at all while the work is performed."
        }
      ]
    },
    {
      "id": "eff05840-dff4-4c93-a865-7b533fc708c9",
      "region": "sjc",
      "subject": "Silicon Valley Scheduled Maintenance - 2026-06-04",
      "start_date": "2026-04-21T17:10:00+00:00",
      "updated_at": "",
      "status": "ongoing",
      "entries": [
        {
          "updated_at": "2026-04-21T17:10:00+00:00",
          "message": "Event Type: Network Upgrade\r\n\r\nWe are performing system changes in the Silicon Valley location during the following scheduled maintenance window. \r\n\r\nStart Time: 2026-06-04 07:05:00 UTC\r\nEnd Time: 2026-06-04 11:05:00 UTC\r\n\r\nWe schedule higher impact maintenance events during off-peak times to reduce impact to customer infrastructure. Our engineers make every effort to minimize system impact, however, network reachability to Silicon Valley instances may be affected for some, or all, of the scheduled maintenance window as we perform this work. While it’s important to be aware of start and end times of the maintenance window, due to our redundant network architecture, our engineers expect that you may see little to no impact at all while the work is performed."
        }
      ]
    }
  ]
}
